{
	"status": true,
	"overview": {
		"sentiment_over_time": {
			"positive": [
				{
					"time": "25-03",
					"count": 16
				},
				{
					"time": "25-03",
					"count": 23
				},
				{
					"time": "23-03",
					"count": 8
				},
				{
					"time": "22-03",
					"count": 7
				},
				{
					"time": "21-03",
					"count": 3
				}
			],
			"negative": [
				{
					"time": "22-03",
					"count": 18
				},
				{
					"time": "23-03",
					"count": 15
				},
				{
					"time": "25-03",
					"count": 12
				},
				{
					"time": "26-03",
					"count": 10
				}
			]
		},
		"source_wise_stats": {
			"facebook": {
				"positive_count": 63,
				"negative_count": 52
			}
		},
		"top_likers": [
			{
				"id": "1411183608952254",
				"name": "Alekhya Devisetty",
				"url": "https://www.facebook.com/app_scoped_user_id/1411183608952254/",
				"score": 2,
				"percentage": 100
			},
			{
				"id": "681739461997824",
				"name": "Roopkanth Kurra",
				"url": "https://www.facebook.com/app_scoped_user_id/681739461997824/",
				"score": 1,
				"percentage": 33
			}
		],
		"top_dis_likers": [
			{
				"id": "1432357440171856",
				"name": "Subhadeep Sarkar",
				"url": "https://www.facebook.com/app_scoped_user_id/1432357440171856/",
				"score": 4,
				"percentage": 82
			},
			{
				"id": "1932587846973178",
				"name": "Lakshmi Prasanna",
				"url": "https://www.facebook.com/app_scoped_user_id/1932587846973178/",
				"score": 2,
				"percentage": 92
			},
			{
				"id": "1476295285775514",
				"name": "Aswini Rao Nunna",
				"url": "https://www.facebook.com/app_scoped_user_id/1476295285775514/",
				"score": 2,
				"percentage": 74
			},
			{
				"id": "1464145113606229",
				"name": "Urvin Desai",
				"url": "https://www.facebook.com/app_scoped_user_id/1464145113606229/",
				"score": 2,
				"percentage": 100
			},
			{
				"id": "508160905939091",
				"name": "Feltso",
				"url": "https://www.facebook.com/feltso/",
				"score": 2,
				"percentage": 67
			}
		],
		"top_pos_posts": [
			{
				"picture": "https://scontent.xx.fbcdn.net/v/t1.0-0/s130x130/17352528_1281364011952106_3795971886140034027_n.jpg?oh=7f49959b2fbc6e59456b0cd226382c66&oe=59699767",
				"permalink_url": "https://www.facebook.com/feltso/posts/1281364011952106:0",
				"message": "We are happy to announce that FeltSo bagged the 'Hot 100 Startups' award by Core Team (Mumbai). We aim to keep this up with the love and support of our followers!",
				"created_time": {
					"date": "2017-03-17 12:14:38.000000",
					"timezone_type": 1,
					"timezone": "+00:00"
				},
				"id": "508160905939091_1281364011952106",
				"score": 8,
				"percentage": 66
			},
			{
				"picture": "https://external.xx.fbcdn.net/safe_image.php?d=AQDpMJiXd_PF__Aa&w=130&h=130&url=http%3A%2F%2Ffeltso.com%2Fblog%2Fwp-content%2Fuploads%2F2017%2F03%2FCustomer-reviews-and-feltso-solution-1.png&cfs=1&_nc_hash=AQBdYgrL0uQ_hk45",
				"permalink_url": "https://www.facebook.com/feltso/posts/1284059291682578",
				"message": "Use FeltSo's AI for the best Experience!\n#AspectBasedSentimentAnalysis\n#FeltSoAI",
				"created_time": {
					"date": "2017-03-20 12:04:29.000000",
					"timezone_type": 1,
					"timezone": "+00:00"
				},
				"id": "508160905939091_1284059291682578",
				"score": 6.7,
				"percentage": 83
			},
			{
				"picture": "https://external.xx.fbcdn.net/safe_image.php?d=AQCVovFw2KlWvOA2&w=130&h=130&url=http%3A%2F%2Ffeltso.com%2Fblog%2Fwp-content%2Fuploads%2F2017%2F03%2FCustomer-Feedback.png&cfs=1&_nc_hash=AQAL5DghbMObUwcy",
				"permalink_url": "https://www.facebook.com/feltso/posts/1277659738989200",
				"message": "Your Target Audience Is The Best Possible Marketing Strategy You Can Have!",
				"created_time": {
					"date": "2017-03-13 13:15:42.000000",
					"timezone_type": 1,
					"timezone": "+00:00"
				},
				"id": "508160905939091_1277659738989200",
				"score": 6.66133814775e-16,
				"percentage": 15
			}
		],
		"top_neg_posts": [
			{
				"picture": "https://external.xx.fbcdn.net/safe_image.php?d=AQDpMJiXd_PF__Aa&w=130&h=130&url=http%3A%2F%2Ffeltso.com%2Fblog%2Fwp-content%2Fuploads%2F2017%2F03%2FCustomer-reviews-and-feltso-solution-1.png&cfs=1&_nc_hash=AQBdYgrL0uQ_hk45",
				"permalink_url": "https://www.facebook.com/feltso/posts/1284059291682578",
				"message": "Use FeltSo's AI for the best Experience!\n#AspectBasedSentimentAnalysis\n#FeltSoAI",
				"created_time": {
					"date": "2017-03-20 12:04:29.000000",
					"timezone_type": 1,
					"timezone": "+00:00"
				},
				"id": "508160905939091_1284059291682578",
				"score": 4.08,
				"percentage": 24
			},
			{
				"picture": "https://external.xx.fbcdn.net/safe_image.php?d=AQCVovFw2KlWvOA2&w=130&h=130&url=http%3A%2F%2Ffeltso.com%2Fblog%2Fwp-content%2Fuploads%2F2017%2F03%2FCustomer-Feedback.png&cfs=1&_nc_hash=AQAL5DghbMObUwcy",
				"permalink_url": "https://www.facebook.com/feltso/posts/1277659738989200",
				"message": "Your Target Audience Is The Best Possible Marketing Strategy You Can Have!",
				"created_time": {
					"date": "2017-03-13 13:15:42.000000",
					"timezone_type": 1,
					"timezone": "+00:00"
				},
				"id": "508160905939091_1277659738989200",
				"score": 1.29,
				"percentage": 13
			},
			{
				"picture": "https://scontent.xx.fbcdn.net/v/t1.0-0/s130x130/17352528_1281364011952106_3795971886140034027_n.jpg?oh=7f49959b2fbc6e59456b0cd226382c66&oe=59699767",
				"permalink_url": "https://www.facebook.com/feltso/posts/1281364011952106:0",
				"message": "We are happy to announce that FeltSo bagged the 'Hot 100 Startups' award by Core Team (Mumbai). We aim to keep this up with the love and support of our followers!",
				"created_time": {
					"date": "2017-03-17 12:14:38.000000",
					"timezone_type": 1,
					"timezone": "+00:00"
				},
				"id": "508160905939091_1281364011952106",
				"score": 0.93,
				"percentage": 7
			}
		],
		"top_pos_comments": [
			{
				"id": "1281364011952106_1289510474470793",
				"text": "Congratulations...!! You deserve it",
				"score": 0.8,
				"created_at": "2017-03-26 04:38:12",
				"user_info": {
					"id": "1411183608952254",
					"name": "Alekhya Devisetty",
					"url": "https://www.facebook.com/app_scoped_user_id/1411183608952254/"
				},
				"post_id": "508160905939091_1281364011952106"
			},
			{
				"id": "1284059291682578_1288826697872504",
				"text": "Great!U r starting with ur customer opinions itself..good idea to start with",
				"score": 0.35,
				"created_at": "2017-03-25 12:46:29",
				"user_info": {
					"id": "681739461997824",
					"name": "Roopkanth Kurra",
					"url": "https://www.facebook.com/app_scoped_user_id/681739461997824/"
				},
				"post_id": "508160905939091_1284059291682578"
			},
			{
				"id": "1284059291682578_1289509544470886",
				"text": "Wow....This is really helpful for identifying fake reviews and to know where the product actually stands....A good one... 👍",
				"score": 0.2,
				"created_at": "2017-03-26 04:36:38",
				"user_info": {
					"id": "1411183608952254",
					"name": "Alekhya Devisetty",
					"url": "https://www.facebook.com/app_scoped_user_id/1411183608952254/"
				},
				"post_id": "508160905939091_1284059291682578"
			}
		],
		"top_neg_comments": [
			{
				"id": "1281364011952106_1286895931398914",
				"text": "AI may not able to solve all the problems",
				"score": 0.8,
				"created_at": "2017-03-23 11:07:37",
				"user_info": {
					"id": "508160905939091",
					"name": "Feltso",
					"url": "https://www.facebook.com/feltso/"
				},
				"post_id": "508160905939091_1281364011952106"
			},
			{
				"id": "1277659738989200_1288658441222663",
				"text": "I dont agree.",
				"score": 0.8,
				"created_at": "2017-03-25 08:19:30",
				"user_info": {
					"id": "1464145113606229",
					"name": "Urvin Desai",
					"url": "https://www.facebook.com/app_scoped_user_id/1464145113606229/"
				},
				"post_id": "508160905939091_1277659738989200"
			},
			{
				"id": "1281364011952106_1286226148132559",
				"text": "Sentiment analysis is still a tough problem to solve",
				"score": 0.8,
				"created_at": "2017-03-22 18:38:43",
				"user_info": {
					"id": "1476295285775514",
					"name": "Aswini Rao Nunna",
					"url": "https://www.facebook.com/app_scoped_user_id/1476295285775514/"
				},
				"post_id": "508160905939091_1281364011952106"
			},
			{
				"id": "1284059291682578_1289820654439775",
				"text": "You guys may have tough time in increasing the accuracy to the maximum..",
				"score": 0.8,
				"created_at": "2017-03-26 13:55:24",
				"user_info": {
					"id": "1932587846973178",
					"name": "Lakshmi Prasanna",
					"url": "https://www.facebook.com/app_scoped_user_id/1932587846973178/"
				},
				"post_id": "508160905939091_1284059291682578"
			},
			{
				"id": "1281364011952106_1286707398084434",
				"text": "Don't know how it solves",
				"score": 0.4,
				"created_at": "2017-03-23 06:37:02",
				"user_info": {
					"id": "1432357440171856",
					"name": "Subhadeep Sarkar",
					"url": "https://www.facebook.com/app_scoped_user_id/1432357440171856/"
				},
				"post_id": "508160905939091_1281364011952106"
			}
		]
	}
}
